setup.cfg
setup.py
mailpile_leap_adapter/__init__.py
mailpile_leap_adapter/auth.py
mailpile_leap_adapter/certs.py
mailpile_leap_adapter/config.py
mailpile_leap_adapter/leap_srp.py
mailpile_leap_adapter/nicknym.py
mailpile_leap_adapter/provider.py
mailpile_leap_adapter/session.py
mailpile_leap_adapter/soledad.py
mailpile_leap_adapter/twisted_patch.py
mailpile_leap_adapter.egg-info/PKG-INFO
mailpile_leap_adapter.egg-info/SOURCES.txt
mailpile_leap_adapter.egg-info/dependency_links.txt
mailpile_leap_adapter.egg-info/not-zip-safe
mailpile_leap_adapter.egg-info/requires.txt
mailpile_leap_adapter.egg-info/top_level.txt