Metadata-Version: 1.1
Name: mailpile-leap-adapter
Version: 0.0.1
Summary: Adapter to directly use LEAP mailboxes with Mailpile
Home-page: http://github.com/pixelated-team/mailpile-leap-adapter
Author: Folker Bernitt
Author-email: fbernitt@thoughtworks.com
License: ALv2
Download-URL: https://github.com/pixelated-team/mailpile-leap-adapter/tarball/0.0.1
Keywords: mailpile,leap,email
Platform: UNKNOWN
Classifier: Development Status :: 3 - Alpha
Classifier: Programming Language :: Python :: 2.7
Classifier: Topic :: Communications :: Email :: Email Clients (MUA)
